akari_bot_webrender/constants/__init__.py
akari_bot_webrender/functions/browser.py
akari_bot_webrender/functions/exceptions.py
akari_bot_webrender/functions/logger.py
akari_bot_webrender/functions/main.py
akari_bot_webrender/functions/options.py
akari_bot_webrender/server/favicon.ico
akari_bot_webrender/server/main.py
akari_bot_webrender/templates/add_count_box.js
akari_bot_webrender/templates/content.html
akari_bot_webrender/templates/custom.css
akari_bot_webrender/templates/element_screenshot_evaluate.js
akari_bot_webrender/templates/section_screenshot_evaluate.js
akari_bot_webrender-0.5.12.dist-info/METADATA
akari_bot_webrender-0.5.12.dist-info/WHEEL
akari_bot_webrender-0.5.12.dist-info/licenses/LICENSE
akari_bot_webrender-0.5.12.dist-info/RECORD
