Metadata-Version: 2.4
Name: akari-bot-webrender
Version: 0.5.12
Summary: 
License-Expression: MIT
License-File: LICENSE
Author: OasisAkari
Author-email: OasisAkari@gmail.com
Requires-Python: >=3.12
Classifier: Programming Language :: Python :: 3
Classifier: Operating System :: OS Independent
Requires-Dist: fastapi (>=0.119.0,<1.0.0)
Requires-Dist: httpx (>=0.28.1)
Requires-Dist: jinja2 (>=3.1.6)
Requires-Dist: loguru (>=0.7.3)
Requires-Dist: orjson (>=3.10.18)
Requires-Dist: playwright (>=1.52.0)
Requires-Dist: pre-commit (>=4.2.0)
Requires-Dist: pydantic (>=2.11.7)
Requires-Dist: tf-playwright-stealth (>=1.2.0)
Requires-Dist: uvicorn (>=0.37.0)
Project-URL: Homepage, https://github.com/Teahouse-Studios/akari-bot-webrender
Project-URL: Issues, https://github.com/Teahouse-Studios/akari-bot-webrender/issues
